imagic2u/__init__.py
imagic2u/editor.py
imagic2u/filtros.py
imagic2u-1.0.dist-info/METADATA
imagic2u-1.0.dist-info/WHEEL
imagic2u-1.0.dist-info/top_level.txt
imagic2u-1.0.dist-info/RECORD
