Metadata-Version: 2.1
Name: imagic2u
Version: 1.0
Summary: Uma biblioteca para manipulação e edição de imagens usando Pillow.
Home-page: https://github.com/R-gu3des
Author: R-gu3des
Author-email: ruan.guedes789@hotmail.com
Classifier: Programming Language :: Python :: 3
Classifier: License :: OSI Approved :: MIT License
Classifier: Operating System :: OS Independent
Requires-Python: >=3.6
Requires-Dist: Pillow
